compclasses/__init__.py
compclasses/_core.py
compclasses/_decorator.py
compclasses/_delegatee.py
compclasses/_logging.py
compclasses/_meta.py
compclasses/py.typed
compclasses-0.4.2.dist-info/METADATA
compclasses-0.4.2.dist-info/WHEEL
compclasses-0.4.2.dist-info/licenses/LICENSE
compclasses-0.4.2.dist-info/RECORD
