Metadata-Version: 2.1
Name: compclasses
Version: 0.4.2
Summary: Prefer composition over inheritance
Project-URL: documentation, https://fbruzzesi.github.io/compclasses/
Project-URL: repository, https://github.com/fbruzzesi/compclasses/
Project-URL: issue-tracker, https://github.com/fbruzzesi/compclasses/issues
Author: Francesco Bruzzesi
License: MIT License
License-File: LICENSE
Classifier: License :: OSI Approved :: MIT License
Classifier: Programming Language :: Python :: 3
Classifier: Programming Language :: Python :: 3.8
Classifier: Programming Language :: Python :: 3.9
Classifier: Programming Language :: Python :: 3.10
Classifier: Programming Language :: Python :: 3.11
Classifier: Programming Language :: Python :: 3.12
Classifier: Topic :: Software Development :: Libraries :: Python Modules
Classifier: Typing :: Typed
Requires-Python: >=3.8
Provides-Extra: all-dev
Requires-Dist: compclasses[dev,docs,test]; extra == 'all-dev'
Provides-Extra: dev
Requires-Dist: hatch; extra == 'dev'
Requires-Dist: pre-commit==2.21.0; extra == 'dev'
Requires-Dist: ruff>=0.1.0; extra == 'dev'
Provides-Extra: docs
Requires-Dist: mkdocs-autorefs; extra == 'docs'
Requires-Dist: mkdocs-material>=9.2.0; extra == 'docs'
Requires-Dist: mkdocs>=1.4.2; extra == 'docs'
Requires-Dist: mkdocstrings[python]>=0.20.0; extra == 'docs'
Provides-Extra: test
Requires-Dist: coverage==7.2.1; extra == 'test'
Requires-Dist: interrogate>=1.5.0; extra == 'test'
Requires-Dist: pytest-xdist==3.2.1; extra == 'test'
Requires-Dist: pytest==7.2.0; extra == 'test'
